{
  "version": "0.0.1",
  "annotation_definitions": [
    {
      "id": "8b3ef246-daa7-4dd5-a0e8-a943f6e7f8c2",
      "name": "keypoints",
      "description": "Produces keypoint annotations for all visible labeled objects that have a humanoid animation avatar component.",
      "format": "json",
      "spec": [
        {
          "template_id": "4a7b253a-334e-460c-bc81-3f4e2c4871c0",
          "template_name": "Coco",
          "key_points": [
            {
              "label": "nose",
              "index": 0,
              "color": {
                "r": 255,
                "g": 0,
                "b": 0,
                "a": 255
              }
            },
            {
              "label": "neck",
              "index": 1,
              "color": {
                "r": 255,
                "g": 87,
                "b": 0,
                "a": 255
              }
            },
            {
              "label": "right_shoulder",
              "index": 2,
              "color": {
                "r": 255,
                "g": 145,
                "b": 0,
                "a": 255
              }
            },
            {
              "label": "right_elbow",
              "index": 3,
              "color": {
                "r": 255,
                "g": 211,
                "b": 0,
                "a": 255
              }
            },
            {
              "label": "right_wrist",
              "index": 4,
              "color": {
                "r": 165,
                "g": 255,
                "b": 0,
                "a": 255
              }
            },
            {
              "label": "left_shoulder",
              "index": 5,
              "color": {
                "r": 84,
                "g": 255,
                "b": 0,
                "a": 255
              }
            },
            {
              "label": "left_elbow",
              "index": 6,
              "color": {
                "r": 13,
                "g": 255,
                "b": 0,
                "a": 255
              }
            },
            {
              "label": "left_wrist",
              "index": 7,
              "color": {
                "r": 0,
                "g": 255,
                "b": 43,
                "a": 255
              }
            },
            {
              "label": "right_hip",
              "index": 8,
              "color": {
                "r": 0,
                "g": 255,
                "b": 93,
                "a": 255
              }
            },
            {
              "label": "right_knee",
              "index": 9,
              "color": {
                "r": 0,
                "g": 255,
                "b": 150,
                "a": 255
              }
            },
            {
              "label": "right_ankle",
              "index": 10,
              "color": {
                "r": 0,
                "g": 255,
                "b": 196,
                "a": 255
              }
            },
            {
              "label": "left_hip",
              "index": 11,
              "color": {
                "r": 0,
                "g": 255,
                "b": 255,
                "a": 255
              }
            },
            {
              "label": "left_knee",
              "index": 12,
              "color": {
                "r": 0,
                "g": 163,
                "b": 255,
                "a": 255
              }
            },
            {
              "label": "left_ankle",
              "index": 13,
              "color": {
                "r": 0,
                "g": 76,
                "b": 255,
                "a": 255
              }
            },
            {
              "label": "right_eye",
              "index": 14,
              "color": {
                "r": 115,
                "g": 0,
                "b": 255,
                "a": 255
              }
            },
            {
              "label": "left_eye",
              "index": 15,
              "color": {
                "r": 242,
                "g": 0,
                "b": 255,
                "a": 255
              }
            },
            {
              "label": "right_ear",
              "index": 16,
              "color": {
                "r": 255,
                "g": 0,
                "b": 154,
                "a": 255
              }
            },
            {
              "label": "left_ear",
              "index": 17,
              "color": {
                "r": 255,
                "g": 0,
                "b": 30,
                "a": 255
              }
            }
          ],
          "skeleton": [
            {
              "joint1": 0,
              "joint2": 1,
              "color": {
                "r": 4,
                "g": 15,
                "b": 159,
                "a": 255
              }
            },
            {
              "joint1": 1,
              "joint2": 2,
              "color": {
                "r": 135,
                "g": 0,
                "b": 19,
                "a": 255
              }
            },
            {
              "joint1": 2,
              "joint2": 3,
              "color": {
                "r": 200,
                "g": 82,
                "b": 20,
                "a": 255
              }
            },
            {
              "joint1": 3,
              "joint2": 4,
              "color": {
                "r": 245,
                "g": 218,
                "b": 0,
                "a": 255
              }
            },
            {
              "joint1": 1,
              "joint2": 5,
              "color": {
                "r": 179,
                "g": 52,
                "b": 29,
                "a": 255
              }
            },
            {
              "joint1": 5,
              "joint2": 6,
              "color": {
                "r": 86,
                "g": 231,
                "b": 66,
                "a": 255
              }
            },
            {
              "joint1": 6,
              "joint2": 7,
              "color": {
                "r": 11,
                "g": 123,
                "b": 9,
                "a": 255
              }
            },
            {
              "joint1": 1,
              "joint2": 8,
              "color": {
                "r": 0,
                "g": 195,
                "b": 59,
                "a": 255
              }
            },
            {
              "joint1": 8,
              "joint2": 9,
              "color": {
                "r": 0,
                "g": 255,
                "b": 84,
                "a": 255
              }
            },
            {
              "joint1": 9,
              "joint2": 10,
              "color": {
                "r": 0,
                "g": 241,
                "b": 182,
                "a": 255
              }
            },
            {
              "joint1": 1,
              "joint2": 11,
              "color": {
                "r": 0,
                "g": 255,
                "b": 255,
                "a": 255
              }
            },
            {
              "joint1": 11,
              "joint2": 12,
              "color": {
                "r": 0,
                "g": 97,
                "b": 241,
                "a": 255
              }
            },
            {
              "joint1": 12,
              "joint2": 13,
              "color": {
                "r": 53,
                "g": 0,
                "b": 183,
                "a": 255
              }
            },
            {
              "joint1": 0,
              "joint2": 14,
              "color": {
                "r": 255,
                "g": 0,
                "b": 226,
                "a": 255
              }
            },
            {
              "joint1": 0,
              "joint2": 15,
              "color": {
                "r": 255,
                "g": 0,
                "b": 208,
                "a": 255
              }
            },
            {
              "joint1": 16,
              "joint2": 14,
              "color": {
                "r": 146,
                "g": 0,
                "b": 255,
                "a": 255
              }
            },
            {
              "joint1": 17,
              "joint2": 15,
              "color": {
                "r": 229,
                "g": 0,
                "b": 33,
                "a": 255
              }
            }
          ]
        }
      ]
    },
    {
      "id": "F66DFD55-FE53-4AA7-8934-B1226D9C9175",
      "name": "keypoints",
      "description": "Produces keypoint annotations for all visible labeled objects that have a humanoid animation avatar component.",
      "format": "json",
      "spec": [
        {
          "template_id": "4a089ea6-2f8e-4d0e-8915-2dfdf95cf743",
          "template_name": "",
          "key_points": [
            {
              "label": "FrontTopLeft",
              "index": 0,
              "color": {
                "r": 255,
                "g": 141,
                "b": 141,
                "a": 255
              }
            },
            {
              "label": "FrontTopRight",
              "index": 1,
              "color": {
                "r": 124,
                "g": 171,
                "b": 240,
                "a": 255
              }
            },
            {
              "label": "FrontBottomLeft",
              "index": 2,
              "color": {
                "r": 124,
                "g": 171,
                "b": 240,
                "a": 255
              }
            },
            {
              "label": "FrontBottomRight",
              "index": 3,
              "color": {
                "r": 124,
                "g": 171,
                "b": 240,
                "a": 255
              }
            },
            {
              "label": "BackTopLeft",
              "index": 4,
              "color": {
                "r": 124,
                "g": 171,
                "b": 240,
                "a": 255
              }
            },
            {
              "label": "BackTopRight",
              "index": 5,
              "color": {
                "r": 124,
                "g": 171,
                "b": 240,
                "a": 255
              }
            },
            {
              "label": "BackBottomLeft",
              "index": 6,
              "color": {
                "r": 124,
                "g": 171,
                "b": 240,
                "a": 255
              }
            },
            {
              "label": "BackBottomRight",
              "index": 7,
              "color": {
                "r": 124,
                "g": 171,
                "b": 240,
                "a": 255
              }
            }
          ],
          "skeleton": []
        }
      ]
    },
    {
      "id": "bounding box",
      "name": "bounding box",
      "description": "Produces 2D bounding box annotations for all visible objects that bear a label defined in this labeler's associated label configuration.",
      "format": "json",
      "spec": [
        {
          "label_id": 1,
          "label_name": "Crate"
        },
        {
          "label_id": 2,
          "label_name": "Cube"
        },
        {
          "label_id": 3,
          "label_name": "Box"
        },
        {
          "label_id": 4,
          "label_name": "Terrain"
        },
        {
          "label_id": 5,
          "label_name": "Character"
        }
      ]
    },
    {
      "id": "bounding box 3D",
      "name": "bounding box 3D",
      "description": "Produces 3D bounding box ground truth data for all visible objects that bear a label defined in this labeler's associated label configuration.",
      "format": "json",
      "spec": [
        {
          "label_id": 1,
          "label_name": "Crate"
        },
        {
          "label_id": 2,
          "label_name": "Cube"
        },
        {
          "label_id": 3,
          "label_name": "Box"
        },
        {
          "label_id": 4,
          "label_name": "Terrain"
        },
        {
          "label_id": 5,
          "label_name": "Character"
        }
      ]
    },
    {
      "id": "instance segmentation",
      "name": "instance segmentation",
      "description": "Produces an instance segmentation image for each frame. The image will render the pixels of each labeled object in a distinct color.",
      "format": "PNG",
      "spec": [
        {
          "label_id": 1,
          "label_name": "Crate"
        },
        {
          "label_id": 2,
          "label_name": "Cube"
        },
        {
          "label_id": 3,
          "label_name": "Box"
        },
        {
          "label_id": 4,
          "label_name": "Terrain"
        },
        {
          "label_id": 5,
          "label_name": "Character"
        }
      ]
    },
    {
      "id": "semantic segmentation",
      "name": "semantic segmentation",
      "description": "Generates a semantic segmentation image for each captured frame. Each object is rendered to the semantic segmentation image using the color associated with it based on this labeler's associated semantic segmentation label configuration. Semantic segmentation images are saved to the dataset in PNG format. Please note that only one SemanticSegmentationLabeler can render at once across all cameras.",
      "format": "PNG",
      "spec": [
        {
          "label_name": "Box",
          "pixel_value": {
            "r": 255,
            "g": 0,
            "b": 0,
            "a": 255
          }
        },
        {
          "label_name": "Cube",
          "pixel_value": {
            "r": 0,
            "g": 6,
            "b": 255,
            "a": 255
          }
        },
        {
          "label_name": "Crate",
          "pixel_value": {
            "r": 0,
            "g": 255,
            "b": 43,
            "a": 255
          }
        },
        {
          "label_name": "Terrain",
          "pixel_value": {
            "r": 209,
            "g": 0,
            "b": 169,
            "a": 255
          }
        }
      ]
    }
  ]
}